devtool_mcp/__init__.py
devtool_mcp-0.6.0.dist-info/METADATA
devtool_mcp-0.6.0.dist-info/WHEEL
devtool_mcp-0.6.0.dist-info/entry_points.txt
devtool_mcp-0.6.0.dist-info/licenses/LICENSE
devtool_mcp-0.6.0.dist-info/RECORD
